sqlmap_ai/__init__.py
sqlmap_ai/adaptive_testing.py
sqlmap_ai/advanced_reporting.py
sqlmap_ai/ai_analyzer.py
sqlmap_ai/cli.py
sqlmap_ai/config_manager.py
sqlmap_ai/enhanced_cli.py
sqlmap_ai/evasion_engine.py
sqlmap_ai/html_reporter.py
sqlmap_ai/main.py
sqlmap_ai/parser.py
sqlmap_ai/run.py
sqlmap_ai/runner.py
sqlmap_ai/security_manager.py
sqlmap_ai/startup.py
sqlmap_ai/timeout_handler.py
sqlmap_ai/ui.py
sqlmap_ai/templates/report_template.html
sqlmap_ai-2.0.7.dist-info/licenses/LICENSE
utils/__init__.py
utils/ai_providers.py
utils/groq_utils.py
sqlmap_ai-2.0.7.dist-info/METADATA
sqlmap_ai-2.0.7.dist-info/WHEEL
sqlmap_ai-2.0.7.dist-info/entry_points.txt
sqlmap_ai-2.0.7.dist-info/top_level.txt
sqlmap_ai-2.0.7.dist-info/RECORD
