Metadata-Version: 2.4
Name: sqlmap-ai
Version: 2.0.7
Summary: AI-powered SQL injection testing tool with multiple AI providers
Home-page: https://github.com/atiilla/sqlmap-ai
Author: Atilla
Author-email: Atilla <attilla@tuta.io>
Maintainer-email: Atilla <attilla@tuta.io>
License-Expression: MIT
Project-URL: Homepage, https://github.com/atiilla/sqlmap-ai
Project-URL: Documentation, https://github.com/atiilla/sqlmap-ai#readme
Project-URL: Repository, https://github.com/atiilla/sqlmap-ai.git
Project-URL: Issues, https://github.com/atiilla/sqlmap-ai/issues
Keywords: sqlmap,sql-injection,security,ai,penetration-testing,cybersecurity
Classifier: Development Status :: 4 - Beta
Classifier: Intended Audience :: Information Technology
Classifier: Intended Audience :: System Administrators
Classifier: Operating System :: OS Independent
Classifier: Programming Language :: Python :: 3
Classifier: Programming Language :: Python :: 3.8
Classifier: Programming Language :: Python :: 3.9
Classifier: Programming Language :: Python :: 3.10
Classifier: Programming Language :: Python :: 3.11
Classifier: Programming Language :: Python :: 3.12
Classifier: Topic :: Security
Classifier: Topic :: System :: Systems Administration
Classifier: Topic :: Internet :: WWW/HTTP :: HTTP Servers
Classifier: Topic :: Software Development :: Testing
Requires-Python: >=3.8
License-File: LICENSE
Requires-Dist: python-dotenv>=1.0.0
Requires-Dist: groq>=0.4.0
Requires-Dist: requests>=2.31.0
Requires-Dist: openai>=1.3.0
Requires-Dist: anthropic>=0.8.0
Requires-Dist: pyyaml>=6.0.1
Requires-Dist: rich>=13.0.0
Requires-Dist: jinja2>=3.1.2
Requires-Dist: cryptography>=3.4.0
Requires-Dist: colorama>=0.4.6
Provides-Extra: dev
Requires-Dist: pytest>=7.0.0; extra == "dev"
Requires-Dist: pytest-asyncio>=0.21.0; extra == "dev"
Requires-Dist: black>=23.0.0; extra == "dev"
Requires-Dist: flake8>=6.0.0; extra == "dev"
Requires-Dist: mypy>=1.0.0; extra == "dev"
Provides-Extra: local-llm
Requires-Dist: transformers>=4.35.0; extra == "local-llm"
Requires-Dist: torch>=2.1.0; extra == "local-llm"
Provides-Extra: reporting
Requires-Dist: plotly>=5.0.0; extra == "reporting"
Requires-Dist: pandas>=2.0.0; extra == "reporting"
Provides-Extra: all
Requires-Dist: pytest>=7.0.0; extra == "all"
Requires-Dist: pytest-asyncio>=0.21.0; extra == "all"
Requires-Dist: black>=23.0.0; extra == "all"
Requires-Dist: flake8>=6.0.0; extra == "all"
Requires-Dist: mypy>=1.0.0; extra == "all"
Requires-Dist: transformers>=4.35.0; extra == "all"
Requires-Dist: torch>=2.1.0; extra == "all"
Requires-Dist: plotly>=5.0.0; extra == "all"
Requires-Dist: pandas>=2.0.0; extra == "all"
Dynamic: author
Dynamic: home-page
Dynamic: license-file
Dynamic: requires-python
